odoo/addons/sale_order_line_multi_warehouse/README.rst
odoo/addons/sale_order_line_multi_warehouse/__init__.py
odoo/addons/sale_order_line_multi_warehouse/__manifest__.py
odoo/addons/sale_order_line_multi_warehouse/i18n/sale_order_line_multi_warehouse.pot
odoo/addons/sale_order_line_multi_warehouse/models/__init__.py
odoo/addons/sale_order_line_multi_warehouse/models/res_company.py
odoo/addons/sale_order_line_multi_warehouse/models/res_config_settings.py
odoo/addons/sale_order_line_multi_warehouse/models/sale_order.py
odoo/addons/sale_order_line_multi_warehouse/models/sale_order_line.py
odoo/addons/sale_order_line_multi_warehouse/models/sale_order_line_warehouse.py
odoo/addons/sale_order_line_multi_warehouse/models/stock_move.py
odoo/addons/sale_order_line_multi_warehouse/models/stock_rule.py
odoo/addons/sale_order_line_multi_warehouse/models/stock_warehouse.py
odoo/addons/sale_order_line_multi_warehouse/readme/CONFIGURE.rst
odoo/addons/sale_order_line_multi_warehouse/readme/CONTRIBUTORS.rst
odoo/addons/sale_order_line_multi_warehouse/readme/DESCRIPTION.rst
odoo/addons/sale_order_line_multi_warehouse/readme/ROADMAP.rst
odoo/addons/sale_order_line_multi_warehouse/readme/USAGE.rst
odoo/addons/sale_order_line_multi_warehouse/security/ir.model.access.csv
odoo/addons/sale_order_line_multi_warehouse/static/description/icon.png
odoo/addons/sale_order_line_multi_warehouse/static/description/index.html
odoo/addons/sale_order_line_multi_warehouse/tests/__init__.py
odoo/addons/sale_order_line_multi_warehouse/tests/test_so_line_multiwarehouse.py
odoo/addons/sale_order_line_multi_warehouse/views/res_config_settings_views.xml
odoo/addons/sale_order_line_multi_warehouse/views/sale_order_line_warehouse_views.xml
odoo/addons/sale_order_line_multi_warehouse/views/sale_order_views.xml
odoo/addons/sale_order_line_multi_warehouse/views/stock_warehouse_views.xml
odoo/addons/sale_order_line_multi_warehouse/wizard/__init__.py
odoo_addon_sale_order_line_multi_warehouse-16.0.1.0.0.2.dist-info/METADATA
odoo_addon_sale_order_line_multi_warehouse-16.0.1.0.0.2.dist-info/WHEEL
odoo_addon_sale_order_line_multi_warehouse-16.0.1.0.0.2.dist-info/top_level.txt
odoo_addon_sale_order_line_multi_warehouse-16.0.1.0.0.2.dist-info/RECORD
